potteringabout/__init__.py
potteringabout/awsutils/__init__.py
potteringabout/awsutils/account.py
potteringabout_awsutils-0.0.1.dist-info/LICENSE
potteringabout_awsutils-0.0.1.dist-info/METADATA
potteringabout_awsutils-0.0.1.dist-info/WHEEL
potteringabout_awsutils-0.0.1.dist-info/top_level.txt
potteringabout_awsutils-0.0.1.dist-info/RECORD
